tgedr/pylib/__init__.py
tgedr/pylib/reddit.py
tgedr/pylib/source.py
tgedr_pylib-0.0.2.dist-info/METADATA
tgedr_pylib-0.0.2.dist-info/WHEEL
tgedr_pylib-0.0.2.dist-info/RECORD
