Metadata-Version: 2.3
Name: tgedr-pylib
Version: 0.0.2
Summary: 
Author: joao tiago viegas
Author-email: jtgv@novonordisk.com
Requires-Python: ~=3.9
Classifier: Programming Language :: Python :: 3
Classifier: Programming Language :: Python :: 3.9
Classifier: Programming Language :: Python :: 3.10
Classifier: Programming Language :: Python :: 3.11
Classifier: Programming Language :: Python :: 3.12
Classifier: Programming Language :: Python :: 3.13
Requires-Dist: pandas (>=2.2.3,<2.3.0)
Requires-Dist: praw (>=7.8.1,<7.9.0)
